genai_utils/__init__.py
genai_utils/config.py
genai_utils/dataframe_tools.py
genai_utils/db_elastic.py
genai_utils/db_elastic1.py
genai_utils/describe_image.py
genai_utils/extract_docs.py
genai_utils/extract_text.py
genai_utils/index_docs.py
genai_utils/index_images_es.py
genai_utils/jsondb.py
genai_utils/ollama_embed.py
genai_utils/pdf_parser.py
genai_utils/rundockeres.sh
genai_utils/version.txt
genai_utils-0.11800000000000002.dist-info/LICENSE
genai_utils-0.11800000000000002.dist-info/METADATA
genai_utils-0.11800000000000002.dist-info/WHEEL
genai_utils-0.11800000000000002.dist-info/top_level.txt
genai_utils-0.11800000000000002.dist-info/RECORD
