Metadata-Version: 2.1
Name: genai_utils
Version: 0.11800000000000002
Summary: Very simple quick way to deploy Django Webservices
Home-page: https://github.com/meyers007/genai_utils.git
Author: Wan Bae, Seattle University
Author-email: baew@seattleu.edu
License: Apache License 2.0
Classifier: Development Status :: 3 - Alpha
Classifier: Intended Audience :: Developers
Classifier: License :: OSI Approved :: Apache Software License
Classifier: Programming Language :: Python :: 3
Classifier: Programming Language :: Python :: 3.8
Classifier: Programming Language :: Python :: 3.11
Classifier: Programming Language :: Python :: 3.12
License-File: LICENSE
